Metadata-Version: 2.1
Name: idchecker
Version: 1.1.2
Summary: IDChecker is a tool to get a list of ID records from 1Password, sorted by expiration date.
Home-page: https://github.com/soulless-viewer/idchecker
Author: Mikalai Lisitsa
Author-email: mikalai.lisitsa@gmail.com
License: MIT
Keywords: 1password op cli
Platform: UNKNOWN
Requires-Python: >=3.6
